swarmauri_tool_jupyterexportpython/JupyterExportPythonTool.py
swarmauri_tool_jupyterexportpython/__init__.py
swarmauri_tool_jupyterexportpython-0.7.5.dist-info/LICENSE
swarmauri_tool_jupyterexportpython-0.7.5.dist-info/METADATA
swarmauri_tool_jupyterexportpython-0.7.5.dist-info/WHEEL
swarmauri_tool_jupyterexportpython-0.7.5.dist-info/entry_points.txt
swarmauri_tool_jupyterexportpython-0.7.5.dist-info/RECORD
